atlas/__init__.py
atlas/__main__.py
atlas/atlas.py
atlas/atlas_manager.py
atlas/atlas_pipeline.py
atlas/load_config.py
atlas/model.py
atlas/commands/__init__.py
atlas/commands/init.py
atlas/commands/model.py
atlas/commands/run.py
atlas/commands/stage.py
atlas/commands/stage_output.py
atlas/commands/stages.py
atlas/utils/__init__.py
atlas/utils/atlas_config.py
atlas/utils/system_utils.py
ml_atlas-0.0.3.data/scripts/atlas.cmd
ml_atlas-0.0.3.dist-info/LICENSE
ml_atlas-0.0.3.dist-info/METADATA
ml_atlas-0.0.3.dist-info/WHEEL
ml_atlas-0.0.3.dist-info/entry_points.txt
ml_atlas-0.0.3.dist-info/top_level.txt
ml_atlas-0.0.3.dist-info/RECORD
